yeonjae_universal_data_storage/__init__.py
yeonjae_universal_data_storage/exceptions.py
yeonjae_universal_data_storage/models.py
yeonjae_universal_data_storage/service.py
yeonjae_universal_data_storage-1.0.5.dist-info/METADATA
yeonjae_universal_data_storage-1.0.5.dist-info/WHEEL
yeonjae_universal_data_storage-1.0.5.dist-info/top_level.txt
yeonjae_universal_data_storage-1.0.5.dist-info/RECORD
